{
  "persona": {
    "John Lin": {
      "movement": [
        2,
        4
      ],
      "pronunciatio": "\ud83d\ude42",
      "description": "preparing materials and resources for the next day's classes, ensuring everything is organized and ready for his students (reviewing the lesson objectives) @ the Ville:Lin family's house:common room:common room table",
      "chat": null,
      "user_action_for_suggestion": "taking a short walk in his garden to enjoy some fresh air and clear his mind before continuing with his tasks (entering the house and removing his shoes)",
      "suggestion": "",
      "eval_res_score": "abstention",
      "eval_res_reason": "abstention"
    },
    "Eddy Lin": {
      "movement": [
        2,
        3
      ],
      "pronunciatio": "\ud83d\udcac",
      "description": "suggestion @ <persona> John Lin",
      "chat": null,
      "user_action_for_suggestion": "John is walking.",
      "suggestion": "Abstention",
      "eval_res_score": "abstention",
      "eval_res_reason": "abstention"
    }
  },
  "meta": {
    "curr_time": "February 13, 2024, 17:00:00",
    "is_john_walking": "yes",
    "number_of_action_tokens": 12
  }
}