{
  "persona": {
    "John Lin": {
      "movement": [
        7,
        3
      ],
      "pronunciatio": "\ud83d\ude42",
      "description": "preparing a homemade lunch, focusing on using fresh and sustainable ingredients from his garden   (setting the table and plating the meal) @ the Ville:Lin family's house:kitchen:cooking area",
      "chat": null,
      "user_action_for_suggestion": "preparing a homemade lunch, focusing on using fresh and sustainable ingredients from his garden   (preparing the main dish using the fresh ingredients)",
      "suggestion": "",
      "eval_res_score": "abstention",
      "eval_res_reason": "abstention"
    },
    "Eddy Lin": {
      "movement": [
        2,
        19
      ],
      "pronunciatio": "\ud83d\udcac",
      "description": "suggestion @ <persona> John Lin",
      "chat": null,
      "user_action_for_suggestion": "John is walking.",
      "suggestion": "Abstention",
      "eval_res_score": "abstention",
      "eval_res_reason": "abstention"
    }
  },
  "meta": {
    "curr_time": "February 13, 2024, 12:45:00",
    "is_john_walking": "yes",
    "number_of_action_tokens": 12
  }
}